{
  "AvatarId": 1,
  "SpriteIdInBattle": 0,
  "SpriteId": 0,
  "Name": "李逍遥",
  "CanAttackAll": false,
  "Level": 1,
  "MaxHP": 150,
  "HP": 150,
  "MaxMP": 100,
  "MP": 100,
  "CoveredBy": 2,
  "WalkFrames": 0,
  "Equipment": {
    "Head": 196,
    "Cloak": 197,
    "Body": 199,
    "Hand": 202,
    "Foot": 202,
    "Ornament": 202
  },
  "BaseAttribute": {
    "AttackStrength": 33,
    "MagicStrength": 20,
    "Defense": 32,
    "Dexterity": 28,
    "FleeRate": 32
  },
  "Resistance": {
    "Poison": 0,
    "Elemental": {
      "Wind": 0,
      "Thunder": 0,
      "Water": 0,
      "Fire": 0,
      "Earth": 0
    }
  },
  "Sound": {
    "Death": 23,
    "Attack": 37,
    "Weapon": 1,
    "Critical": 5,
    "Magic": 9,
    "Cover": 15,
    "Dying": 19
  },
  "Script": {
    "FriendDeath": "Hero_00001_Death",
    "Dying": ""
  },
  "Magic": {
    "Cooperative": 85,
    "Learned": [
      3,
      0,
      0,
      0,
      0,
      0,
      0,
      0,
      0,
      0,
      0,
      0,
      0,
      0,
      0,
      0,
      0,
      0,
      0,
      0,
      0,
      0,
      0,
      0,
      0,
      0,
      0,
      0,
      0,
      0,
      0,
      0
    ],
    "Learnable": [
      {
        "Level": 7,
        "MagicId": 51
      },
      {
        "Level": 8,
        "MagicId": 18
      },
      {
        "Level": 10,
        "MagicId": 5
      },
      {
        "Level": 12,
        "MagicId": 49
      },
      {
        "Level": 17,
        "MagicId": 6
      },
      {
        "Level": 20,
        "MagicId": 17
      },
      {
        "Level": 22,
        "MagicId": 30005
      },
      {
        "Level": 26,
        "MagicId": 90
      },
      {
        "Level": 34,
        "MagicId": 30007
      }
    ]
  }
}